tunned_geobr-1.1.3.dist-info/METADATA
tunned_geobr-1.1.3.dist-info/WHEEL
tunned_geobr-1.1.3.dist-info/entry_points.txt
tunned_geobr-1.1.3.dist-info/licenses/LICENSE.txt
tunned_geobr/__init__.py
tunned_geobr/data/grid_state_correspondence_table.csv
tunned_geobr/list_geobr.py
tunned_geobr/lookup_muni.py
tunned_geobr/read_2d_seismic.py
tunned_geobr/read_3d_seismic.py
tunned_geobr/read_ama_anemometric_towers.py
tunned_geobr/read_amazon.py
tunned_geobr/read_amazon_ibas.py
tunned_geobr/read_apcb_amazon.py
tunned_geobr/read_apcb_caatinga.py
tunned_geobr/read_apcb_cerrado_pantanal.py
tunned_geobr/read_apcb_mata_atlantica.py
tunned_geobr/read_apcb_pampa.py
tunned_geobr/read_apcb_zcm.py
tunned_geobr/read_archaeological_sites.py
tunned_geobr/read_areas_under_contract.py
tunned_geobr/read_atlantic_forest_ibas.py
tunned_geobr/read_atlantic_forest_law_limits.py
tunned_geobr/read_baze_sites.py
tunned_geobr/read_biodiesel_plants.py
tunned_geobr/read_biomes.py
tunned_geobr/read_biomethane_plants.py
tunned_geobr/read_biosphere_reserves.py
tunned_geobr/read_cave_potential.py
tunned_geobr/read_census_tract.py
tunned_geobr/read_climate.py
tunned_geobr/read_climate_aggressiveness.py
tunned_geobr/read_comparable_areas.py
tunned_geobr/read_compression_stations.py
tunned_geobr/read_conservation_units.py
tunned_geobr/read_conservation_units_without_delimitation.py
tunned_geobr/read_country.py
tunned_geobr/read_dams_ana.py
tunned_geobr/read_disaster_risk_area.py
tunned_geobr/read_drainage_ducts.py
tunned_geobr/read_dup.py
tunned_geobr/read_ebas.py
tunned_geobr/read_economically_navigable_inland_waterways.py
tunned_geobr/read_etanol_plants.py
tunned_geobr/read_existent_biomass_ute.py
tunned_geobr/read_existent_cgh.py
tunned_geobr/read_existent_eolic.py
tunned_geobr/read_existent_fossile_ute.py
tunned_geobr/read_existent_nuclear_ute.py
tunned_geobr/read_existent_pch.py
tunned_geobr/read_existent_solar.py
tunned_geobr/read_existent_substations.py
tunned_geobr/read_existent_transmission_lines.py
tunned_geobr/read_existent_uhe.py
tunned_geobr/read_exploration_blocks.py
tunned_geobr/read_exploration_production_environment.py
tunned_geobr/read_federal_highways.py
tunned_geobr-1.1.3.dist-info/RECORD
