Metadata-Version: 2.1
Name: tunned-geobr
Version: 1.1.3
Summary: Fork personalizado do geobr com funcionalidades extras como download de dados da ANM
Author: Anderson Stolfi
License: MIT
Classifier: Intended Audience :: Science/Research
Classifier: Intended Audience :: Developers
Classifier: Intended Audience :: Education
Classifier: Topic :: Scientific/Engineering :: GIS
Classifier: Topic :: Scientific/Engineering :: Visualization
Classifier: Programming Language :: Python
Project-URL: homepage, https://github.com/popogis24/tunned_geobr
Project-URL: repository, https://github.com/popogis24/tunned_geobr
Requires-Python: <4.0,>=3.9
Requires-Dist: geopandas<=1.1,>=1.0.0
Requires-Dist: shapely<=2.1.0,>=1.7.0
Requires-Dist: requests<3.0.0,>=2.25.1
Requires-Dist: lxml<6.0.0,>=5.1.0
Requires-Dist: html5lib==1.1
Requires-Dist: geobr<0.3.0,>=0.2.2
Requires-Dist: patool>=1.15.0
Requires-Dist: fiona>=1.10.1
Requires-Dist: gdown>=5.2.0
Requires-Dist: tabulate>=0.9.0
Requires-Dist: pyarrow>=20.0.0
Requires-Dist: free-proxy>=1.1.3
Requires-Dist: dask-geopandas>=0.4.2
Requires-Dist: cloudscraper>=1.2.71
Requires-Dist: openpyxl>=3.1.5
